seqpat/__init__.py
seqpat/patterns.py
seqpat/utility_functions.py
seqpat-0.1.1.dist-info/LICENSE.txt
seqpat-0.1.1.dist-info/METADATA
seqpat-0.1.1.dist-info/WHEEL
seqpat-0.1.1.dist-info/top_level.txt
seqpat-0.1.1.dist-info/RECORD
