Metadata-Version: 2.1
Name: seqpat
Version: 0.1.1
Summary: Parser for string sequence, inspired by reguar expressions
Author-email: Toshihiro Kamiya <kamiya@mbj.nifty.com>
License: MIT License
Project-URL: homepage, https://github.com/tos-kamiya/seqpat
Project-URL: repository, https://github.com/tos-kamiya/seqpat
Classifier: Development Status :: 3 - Alpha
Classifier: Intended Audience :: Developers
Classifier: License :: OSI Approved :: MIT License
Classifier: Programming Language :: Python :: 3.10
Classifier: Operating System :: POSIX :: Linux
Requires-Python: >=3.10
License-File: LICENSE.txt
